setup.py
colorpalette_master.egg-info/PKG-INFO
colorpalette_master.egg-info/SOURCES.txt
colorpalette_master.egg-info/dependency_links.txt
colorpalette_master.egg-info/requires.txt
colorpalette_master.egg-info/top_level.txt
cpmaster/ImageCreation.py
cpmaster/MMCQ.py
cpmaster/___main___.py
cpmaster/__init__.py