Metadata-Version: 2.1
Name: colorpalette-master
Version: 0.0.8
Summary: Scripts for generating a color palette out of an image
Home-page: https://github.com/gejirz/colorpalette-master
Author: Victor Andrievskiy
Author-email: superavb222@gmail.com
License: MIT License
Keywords: python,color palette,median cut quantization,PixPalette,median cut
Platform: UNKNOWN
